CHANGES.txt
README.txt
__init__.py
setup.py
unweb/__init__.py
unweb.recipe.uwsgi.egg-info/PKG-INFO
unweb.recipe.uwsgi.egg-info/SOURCES.txt
unweb.recipe.uwsgi.egg-info/dependency_links.txt
unweb.recipe.uwsgi.egg-info/entry_points.txt
unweb.recipe.uwsgi.egg-info/not-zip-safe
unweb.recipe.uwsgi.egg-info/requires.txt
unweb.recipe.uwsgi.egg-info/top_level.txt
unweb/recipe/__init__.py
unweb/recipe/uwsgi/__init__.py