Metadata-Version: 1.0
Name: unweb.recipe.uwsgi
Version: 0.4
Summary:             This is a recipe to build a uwsgi binary as well as the xml config file.
Home-page: https://github.com/unweb/unweb.recipe.uwsgi
Author: Dimitris Moraitis
Author-email: dimo@unweb.me
License: BSD
Keywords: buildout,uwsgi
Platform: UNKNOWN
Classifier: Framework :: Buildout
Classifier: Topic :: Software Development :: Build Tools
Classifier: Development Status :: 5 - Production/Stable
Classifier: License :: OSI Approved :: BSD License
Classifier: Programming Language :: Python :: 2.5
Classifier: Programming Language :: Python :: 2.6
Classifier: Programming Language :: Python :: 2.7
